Workbook
Name DiscountRate: Assumptions!$E$10

Sheet Assumptions
A1: Driver | B1: 2024 | C1: 2025 | D1: 2026
A2: Units | B2: 100 | C2: 140 | D2: 130
A3: Price | B3: 8.5 | C3: 8.7 | D3: 9
A4: Cost per unit | B4: 3.2 | C4: 3.4 | D4: 3.5
B10: Discount rate | E10: 0.1
B11: Stress discount rate | E11: 0.12

Sheet Revenue
A1: Metric | B1: 2024 | C1: 2025 | D1: 2026
A5: Units | B5: =Assumptions!B2 | C5: =Assumptions!C2 | D5: =Assumptions!D2
A6: Price | B6: =Assumptions!B3 | C6: =Assumptions!C3 | D6: =Assumptions!D3
A8: Revenue | B8: =B5*B6 | C8: =C5*C6 | D8: =D5*D6
A9: Cost of goods | B9: =B5*Assumptions!B4 | C9: =C5*Assumptions!C4 | D9: =D5*Assumptions!D4
A10: Gross profit | B10: =B8-B9 | C10: =C8-C9 | D10: =D8-D9

Sheet Summary
A1: Metric | B1: 2024 | C1: 2025 | D1: 2026
A5: Revenue | B5: =Revenue!B8 | C5: =Revenue!C8 | D5: =Revenue!D8
A6: Gross profit | B6: =Revenue!B10 | C6: =Revenue!C10 | D6: =Revenue!D10
A8: Units source | B8: =Assumptions!B2 | C8: =Assumptions!C2 | D8: =Assumptions!D2
A10: Discounted gross profit | B10: =B6*(1-DiscountRate) | C10: =C6*(1-DiscountRate) | D10: =D6*(1-DiscountRate)

Sheet Dashboard
A1: Board dashboard
A4: 2025 gross profit | B4: =Summary!C6
A5: 2025 discounted gross profit | B5: =Summary!C10
